Metadata-Version: 1.0
Name: deep-mapper1
Version: 0.0.1
Summary: This is a fork of gebriallairbeg/deep_mapper. It is able to return an object with converted keys, or a list of objects
Home-page: http://github.com/cao5zy/deep_mapper
Author: zongying.cao
Author-email: zongying_cao@163.com
License: MIT
Platform: UNKNOWN
